TgEntities2html/__init__.py
TgEntities2html-0.1.dist-info/METADATA
TgEntities2html-0.1.dist-info/WHEEL
TgEntities2html-0.1.dist-info/top_level.txt
TgEntities2html-0.1.dist-info/RECORD
