Metadata-Version: 2.1
Name: TgEntities2html
Version: 0.1
Summary: Parse any Telegram message to html
Home-page: http://github.com/4nt0n10M4/TgEntities2html
Author: Antonio M A
Author-email: antonio.ma40869441@gmail.com
License: gpl-3.0
Platform: UNKNOWN
